medmask/__init__.py
medmask/_version.py
medmask/compression/__init__.py
medmask/compression/zstd_codec.py
medmask/core/__init__.py
medmask/core/mapping.py
medmask/core/segmask.py
medmask/storage/__init__.py
medmask/storage/archivefile.py
medmask/storage/maskfile.py
medmask/utils/__init__.py
medmask/utils/utils.py
medmask-0.1.3.dist-info/METADATA
medmask-0.1.3.dist-info/WHEEL
medmask-0.1.3.dist-info/top_level.txt
medmask-0.1.3.dist-info/RECORD
