Metadata-Version: 2.4
Name: medmask
Version: 0.1.3
Summary: Medical Image Mask Compression and Processing Library
Author-email: "Fastdiag.ai" <contact@fastdiag.ai>
License: MIT
Keywords: medical-imaging,segmentation,compression,mask-processing
Classifier: Development Status :: 4 - Beta
Classifier: Intended Audience :: Developers
Classifier: Intended Audience :: Healthcare Industry
Classifier: Intended Audience :: Science/Research
Classifier: Operating System :: OS Independent
Classifier: Programming Language :: Python :: 3
Classifier: Programming Language :: Python :: 3.8
Classifier: Programming Language :: Python :: 3.9
Classifier: Programming Language :: Python :: 3.10
Classifier: Programming Language :: Python :: 3.11
Classifier: Programming Language :: Python :: 3.12
Classifier: Topic :: Scientific/Engineering :: Medical Science Apps.
Classifier: Topic :: Software Development :: Libraries :: Python Modules
Requires-Python: >=3.8
Requires-Dist: numpy>=1.19.0
Requires-Dist: zstandard>=0.15.0
Requires-Dist: spacetransformer-core>=0.1.0
Provides-Extra: test
Requires-Dist: pytest>=6.0; extra == "test"
Provides-Extra: dev
Requires-Dist: pytest>=6.0; extra == "dev"
Provides-Extra: examples
Requires-Dist: nibabel>=3.0; extra == "examples"
Requires-Dist: jupyter>=1.0; extra == "examples"
Requires-Dist: matplotlib>=3.0; extra == "examples"
